Workbook

Sheet INSTRUCTIVO LLAMADAS
A1: Llamadas seguimiento pacientes Atención Domiciliaria: Buenos días/tardes, habla con el auditor XXXXX XXXXXX, me comunica por favor con el paciente XXXX XXXX o familiar. ¿con quién tengo el gusto? Xxxxxx ¿Qué parentesco tiene con el paciente? Xxxxxxx. El motivo de mi llamada es con el fin de confirmar que a el/la paciente Néstor Pérez, se le esté prestando correctamente y a tiempo los servicios asignados. Me confirma por favor ¿Quién ha asistido hasta el momento? Gracias, ¿de estos servicios ya prestados, tiene alguna duda o inconformidad? ¿tiene alguna sugerencia que desee registrar en la llamada? Agradezco su información y su tiempo

Sheet Formato Seguimiento PHD
A1: REGIONAL | B1: MUNICIPIO | C1: DIRECCION | D1: BARRIO | E1: FECHA dd/mm/aa | F1: IPS QUE ATIENDE AL PACIENTE | G1: NOMBRE DEL PACIENTE | H1: TIPO DE DOCUMENTO | I1: NUMERO DOCUMENTO | J1: TELEFONO 1 | K1: TELEFONO 2 | L1: CIE_10 | M1: DESCRIPCION CIE_10 | N1: COMPLEJIDAD | O1: TIPO DE INTERVENCION | P1: NUMERO DE VISITAS POR DIA | Q1: NOMBRE DE QUIEN ATIENDE LA LLAMADA | R1: PARENTESCO | S1: COMENTARIOS | T1: EFECTIVIDAD DE LA LLAMADA | U1: INTENTOS | AB1: TIPO
A2: CORDOBA | B2: MONTERIA | C2: B/ VILLA SORRENTO | D2: Mz7 L.10 | E2: 43221 | F2: MICASA MI HOSPITAL DE LA SABANA | G2: PAOLA HERNANDEZ VEGA | H2: CC | I2: 50919775 | J2: 3007763838 | L2: G822 | M2: =VLOOKUP(L2,[1]CIE10!$A:$C,3,0) -> PARAPLEJIA, NO ESPECIFICADA | N2: CRONICO | O2: ENFERMERA 12 H | P2: 1 | Q2: PAOLA HERNANDEZ | R2: PACIENTE
A3: CORDOBA | B3: MONTERIA | C3: B/ VILLA SORRENTO | D3: Mz7 L.10 | E3: 43221 | F3: MICASA MI HOSPITAL DE LA SABANA | G3: PAOLA HERNANDEZ VEGA | H3: CC | I3: 50919775 | J3: 3007763838 | L3: G822 | M3: =VLOOKUP(L3,[1]CIE10!$A:$C,3,0) -> PARAPLEJIA, NO ESPECIFICADA | N3: CRONICO | O3: TER. FISICA | P3: 1 | Q3: PAOLA HERNANDEZ | R3: PACIENTE
A4: CORDOBA | B4: BUENAVISTA | C4: VEREDA COSTA RICA | D4: casa finca | E4: 43221 | F4: MICASA MI HOSPITAL DE LA SABANA | G4: LINA MARCELA TAMARA ORTIZ | H4: C.C | I4: 1067097250 | J4: 3215039052 | L4: G800 | M4: =VLOOKUP(L4,[1]CIE10!$A:$C,3,0) -> PARALISIS CEREBRAL ESPASTICA | N4: CRONICO | O4: ENFERMERA 24 H | P4: 1 | Q4: CENITH ORTIZ OYOLA | R4: MADRE
A5: CORDOBA | B5: BUENAVISTA | C5: VEREDA COSTA RICA | D5: casa finca | E5: 43221 | F5: MICASA MI HOSPITAL DE LA SABANA | G5: LINA MARCELA TAMARA ORTIZ | H5: C.C | I5: 1067097250 | J5: 3215039052 | L5: G800 | M5: =VLOOKUP(L5,[1]CIE10!$A:$C,3,0) -> PARALISIS CEREBRAL ESPASTICA | N5: CRONICO | O5: TER. FISICA | P5: 1 | Q5: CENITH ORTIZ OYOLA | R5: MADRE
A6: CORDOBA | B6: BUENAVISTA | C6: VEREDA COSTA RICA | D6: casa finca | E6: 43221 | F6: MICASA MI HOSPITAL DE LA SABANA | G6: LINA MARCELA TAMARA ORTIZ | H6: C.C | I6: 1067097250 | J6: 3215039052 | L6: G800 | M6: =VLOOKUP(L6,[1]CIE10!$A:$C,3,0) -> PARALISIS CEREBRAL ESPASTICA | N6: CRONICO | O6: VISITA MED. GENERAL | P6: 1 | Q6: CENITH ORTIZ OYOLA | R6: MADRE
A7: CORDOBA | B7: MONTERIA | C7: VIVIENDA IPS | D7: calle 13#4-41 | E7: 43221 | F7: MICASA MI HOSPITAL DE LA SABANA | G7: CAMILA CHAMORRO ESTRADA | H7: TI | I7: 1151452288 | J7: 3136252893 | K7: 3117320678 | L7: G800 | M7: =VLOOKUP(L7,[1]CIE10!$A:$C,3,0) -> PARALISIS CEREBRAL ESPASTICA | N7: CRONICO | O7: VISITA MED. GENERAL | P7: 1 | Q7: YOLFARIS ESTRADA | R7: MADRE
A8: CORDOBA | B8: MONTERIA | C8: VIVIENDA IPS | D8: calle 13#4-41 | E8: 43221 | F8: MICASA MI HOSPITAL DE LA SABANA | G8: CAMILA CHAMORRO ESTRADA | H8: TI | I8: 1151452288 | J8: 3136252893 | K8: 3117320678 | L8: G800 | M8: =VLOOKUP(L8,[1]CIE10!$A:$C,3,0) -> PARALISIS CEREBRAL ESPASTICA | N8: CRONICO | O8: ENFERMERA 24 H | P8: 1 | Q8: YOLFARIS ESTRADA | R8: MADRE
A9: CORDOBA | B9: MONTERIA | C9: VIVIENDA IPS | D9: calle 13#4-41 | E9: 43221 | F9: MICASA MI HOSPITAL DE LA SABANA | G9: CAMILA CHAMORRO ESTRADA | H9: TI | I9: 1151452288 | J9: 3136252893 | K9: 3117320678 | L9: G800 | M9: =VLOOKUP(L9,[1]CIE10!$A:$C,3,0) -> PARALISIS CEREBRAL ESPASTICA | N9: CRONICO | O9: TER. FISICA | P9: 2 | Q9: YOLFARIS ESTRADA | R9: MADRE
A10: CORDOBA | B10: MONTERIA | C10: VIVIENDA IPS | D10: calle 13#4-41 | E10: 43221 | F10: MICASA MI HOSPITAL DE LA SABANA | G10: CAMILA CHAMORRO ESTRADA | H10: TI | I10: 1151452288 | J10: 3136252893 | K10: 3117320678 | L10: G800 | M10: =VLOOKUP(L10,[1]CIE10!$A:$C,3,0) -> PARALISIS CEREBRAL ESPASTICA | N10: CRONICO | O10: TER. LENGUAJE | P10: 1 | Q10: YOLFARIS ESTRADA | R10: MADRE
A11: CORDOBA | B11: MONTERIA | C11: VIVIENDA IPS | D11: calle 13#4-41 | E11: 43221 | F11: MICASA MI HOSPITAL DE LA SABANA | G11: CAMILA CHAMORRO ESTRADA | H11: TI | I11: 1151452288 | J11: 3136252893 | K11: 3117320678 | L11: G800 | M11: =VLOOKUP(L11,[1]CIE10!$A:$C,3,0) -> PARALISIS CEREBRAL ESPASTICA | N11: CRONICO | O11: TER. RESPIRATORIO | P11: 1 | Q11: YOLFARIS ESTRADA | R11: MADRE
A12: CORDOBA | B12: MONTERIA | C12: B/SANTA FE | D12: MZ 12 L.9 | E12: 43221 | F12: MICASA MI HOSPITAL DE LA SABANA | G12: YARA BARRIENTOS VALVERDE | H12: CC | I12: 50931108 | J12: 3123386830 | K12: 3106939251 | L12: G822 | M12: =VLOOKUP(L12,[1]CIE10!$A:$C,3,0) -> PARAPLEJIA, NO ESPECIFICADA | N12: CRONICO | O12: TER. FISICA | P12: 1 | Q12: DOLORES BARRIENTOS | R12: MADRE
A13: CORDOBA | B13: MONTERIA | C13: B/VILLA MELISA | D13: Mz.45 L.14 | E13: 43241 | F13: MICASA MI HOSPITAL DE LA SABANA | G13: LISBELLY VARGAS TOVAR | H13: CC | I13: 1067944075 | J13: 3173214269 | L13: G402 | M13: =VLOOKUP(L13,'CIE10'!$A:$C,3,0) -> EPILEPSIA Y SINDROMES EPILEPTICOS SINTOMATICOS RELACIONADOS CON LOCALIZACIONES (FOCALES) (PARCIALES) Y CON ATAQUES PARCIALES COMPLEJOS | N13: CRONICO | O13: VISITA MED. GENERAL | P13: 1 | Q13: ANA MILENA TOVAR | R13: MADRE
A14: CORDOBA | B14: MONTERIA | C14: B/SANTA ELENA 4 | D14: A29#40-74 | E14: 43210 | F14: MICASA MI HOSPITAL DE LA SABANA | G14: LUIS FERNANDO LOPEZ ARTEAGA | H14: CC | I14: 10967175 | J14: 3106432129 | L14: G822 | M14: =VLOOKUP(L14,'CIE10'!$A:$C,3,0) -> PARAPLEJIA, NO ESPECIFICADA | N14: CRONICO | O14: TER. FISICA | P14: 1 | Q14: LUIS FERNANDO LOPEZ | R14: PACIENTE
A15: CORDOBA | B15: MONTERIA | C15: B/SANTA ELENA 4 | D15: A29#40-74 | E15: 43210 | F15: MICASA MI HOSPITAL DE LA SABANA | G15: LUIS FERNANDO LOPEZ ARTEAGA | H15: CC | I15: 10967175 | J15: 3106432129 | L15: G822 | M15: =VLOOKUP(L15,'CIE10'!$A:$C,3,0) -> PARAPLEJIA, NO ESPECIFICADA | N15: CRONICO | O15: TER. FISICA | P15: 1 | Q15: LUIS FERNANDO LOPEZ | R15: PACIENTE
M16: =VLOOKUP(L16,'CIE10'!$A:$C,3,0) -> #N/A
M17: =VLOOKUP(L17,'CIE10'!$A:$C,3,0) -> #N/A
M18: =VLOOKUP(L18,'CIE10'!$A:$C,3,0) -> #N/A
M19: =VLOOKUP(L19,'CIE10'!$A:$C,3,0) -> #N/A
M20: =VLOOKUP(L20,'CIE10'!$A:$C,3,0) -> #N/A
M21: =VLOOKUP(L21,'CIE10'!$A:$C,3,0) -> #N/A
M22: =VLOOKUP(L22,'CIE10'!$A:$C,3,0) -> #N/A
M23: =VLOOKUP(L23,'CIE10'!$A:$C,3,0) -> #N/A
M24: =VLOOKUP(L24,'CIE10'!$A:$C,3,0) -> #N/A
M25: =VLOOKUP(L25,'CIE10'!$A:$C,3,0) -> #N/A
M26: =VLOOKUP(L26,'CIE10'!$A:$C,3,0) -> #N/A
M27: =VLOOKUP(L27,'CIE10'!$A:$C,3,0) -> #N/A
... M635: =VLOOKUP(L635,'CIE10'!$A:$C,3,0) -> #N/A

Sheet Formato Visita PHD
A1: SEGUIMIENTO ATENCION DOMICILIARIA
A2: NOMBRE Y APELLIDOS DEL PACIENTE | C2: TIPO DE DOCUMENTO | D2: NUMERO DE DOCUMENTO
A4: EDAD: | C4: SEXO:
A5: DIRECCION DOMICILIO | C5: TELEFONOS
A6: DEPARTAMENTO | C6: MUNICIPIO
A7: FECHA DE LA VISITA | C7: HORA DE LA VISITA
A8: IPS PACIENTE
A9: NOMBRE DE QUIEN RECIBE LA VISITA
A10: PARENTESCO
A11: DIAGNOSTICO
A14: TRATAMIENTO INSTAURADO
A18: HALLAZGOS
A30: OBSERVACIONES, COMENTARIOS Y SUGERENCIAS DE AUDITORIA
A37: OBSERVACIONES, COMENTARIOS Y SUGERENCIAS DEL CUIDADOR
A39: NOMBRE AUDITOR

Sheet CIE10
A1: Código | B1: Simbolo | C1: Descripcion | D1: Sexo | E1: Límite inferior | F1: Límite superior | G1: No son afección principal | H1: Observaciones
A2: A000 | C2: COLERA DEBIDO A VIBRIO CHOLERAE O1, BIOTIPO CHOLERAE | D2: AMBOS | E2: 0 | F2: 0
A3: A001 | C3: COLERA DEBIDO A VIBRIO CHOLERAE O1, BIOTIPO EL TOR | D3: AMBOS | E3: 0 | F3: 0
A4: A009 | C4: COLERA NO ESPECIFICADO | D4: AMBOS | E4: 0 | F4: 0
A5: A010 | C5: FIEBRE TIFOIDEA | D5: AMBOS | E5: 0 | F5: 0
A6: A011 | C6: FIEBRE PARATIFOIDEA A | D6: AMBOS | E6: 0 | F6: 0
A7: A012 | C7: FIEBRE PARATIFOIDEA B | D7: AMBOS | E7: 0 | F7: 0
A8: A013 | C8: FIEBRE PARATIFOIDEA C | D8: AMBOS | E8: 0 | F8: 0
A9: A014 | C9: FIEBRE PARATIFOIDEA, NO ESPECIFICADA | D9: AMBOS | E9: 0 | F9: 0
A10: A020 | C10: ENTERITIS DEBIDA A SALMONELLA | D10: AMBOS | E10: 0 | F10: 0
A11: A021 | C11: SEPTICEMIA DEBIDA A SALMONELLA | D11: AMBOS | E11: 0 | F11: 0
A12: A022 | B12: † | C12: INFECCIONES LOCALIZADAS DEBIDA A SALMONELLA | D12: AMBOS | E12: 0 | F12: 0
A13: A028 | C13: OTRAS INFECCIONES ESPECIFICADAS COMO DEBIDAS A SALMONELLA | D13: AMBOS | E13: 0 | F13: 0
A14: A029 | C14: INFECCION DEBIDA A SALMONELLA NO ESPECIFICADA | D14: AMBOS | E14: 0 | F14: 0
A15: A030 | C15: SHIGELOSIS DEBIDA A SHIGELLA DYSENTERIAE | D15: AMBOS | E15: 0 | F15: 0
A16: A031 | C16: SHIGELOSIS DEBIDA A SHIGELLA FLEXNERI | D16: AMBOS | E16: 0 | F16: 0
A17: A032 | C17: SHIGELOSIS DEBIDA A SHIGELLA BOYDII | D17: AMBOS | E17: 0 | F17: 0
A18: A033 | C18: SHIGELOSIS DEBIDA A SHIGELLA SONNEI | D18: AMBOS | E18: 0 | F18: 0
A19: A038 | C19: OTRAS SHIGELOSIS | D19: AMBOS | E19: 0 | F19: 0
A20: A039 | C20: SHIGELOSIS DE TIPO NO ESPECIFICADO | D20: AMBOS | E20: 0 | F20: 0
A21: A040 | C21: INFECCION DEBIDA A ESCHERICHIA COLI ENTEROPATOGENA | D21: AMBOS | E21: 0 | F21: 0
A22: A041 | C22: INFECCION DEBIDA A ESCHERICHIA COLI ENTEROTOXIGENA | D22: AMBOS | E22: 0 | F22: 0
A23: A042 | C23: INFECCION DEBIDA A ESCHERICHIA COLI ENTEROINVASIVA | D23: AMBOS | E23: 0 | F23: 0
A24: A043 | C24: INFECCION DEBIDA A ESCHERICHIA COLI ENTEROHEMORRAGICA | D24: AMBOS | E24: 0 | F24: 0
... A42: A064 | C42: ABSCESO AMEBIANO DEL HIGADO | D42: AMBOS | E42: 0 | F42: 0
A43: A065 | B43: † | C43: ABSCESO AMEBIANO DEL PULMON (J99.8*) | D43: AMBOS | E43: 0 | F43: 0
A44: A066 | B44: † | C44: ABSCESO AMEBIANO DEL CEREBRO (G07*) | D44: AMBOS | E44: 0 | F44: 0
A45: A067 | C45: AMEBIASIS CUTANEA | D45: AMBOS | E45: 0 | F45: 0
A46: A068 | C46: INFECCION AMEBIANA DE OTRAS LOCALIZACIONES | D46: AMBOS | E46: 0 | F46: 0
A47: A069 | C47: AMEBIASIS, NO ESPECIFICADA | D47: AMBOS | E47: 0 | F47: 0
A48: A070 | C48: BALANTIDIASIS | D48: AMBOS | E48: 0 | F48: 0
A49: A071 | C49: GIARDIASIS [LAMBLIASIS] | D49: AMBOS | E49: 0 | F49: 0
A50: A072 | C50: CRIPTOSPORIDIOSIS | D50: AMBOS | E50: 0 | F50: 0
A51: A073 | C51: ISOSPORIASIS | D51: AMBOS | E51: 0 | F51: 0
A52: A078 | C52: OTRAS ENFERMEDADES INTESTINALES ESPECIFICADAS DEBIDAS A PROTOZOARIOS | D52: AMBOS | E52: 0 | F52: 0
A53: A079 | C53: ENFERMEDAD INTESTINAL DEBIDA A PROTOZOARIOS, NO ESPECIFICADA | D53: AMBOS | E53: 0 | F53: 0
A54: A080 | C54: ENTERITIS DEBIDA A ROTAVIRUS | D54: AMBOS | E54: 0 | F54: 0
A55: A081 | C55: GASTROENTEROPATIA AGUDA DEBIDA AL AGENTE DE NORWALK | D55: AMBOS | E55: 0 | F55: 0
A56: A082 | C56: ENTERITIS DEBIDA A ADENOVIRUS | D56: AMBOS | E56: 0 | F56: 0
... A60: A09X | C60: DIARREA Y GASTROENTERITIS DE PRESUNTO ORIGEN INFECCIOSO | D60: AMBOS | E60: 0 | F60: 0
A61: A150 | C61: TUBERCULOSIS DEL PULMON, CONFIRMADA POR HALLAZGO MICROSCOPICO DEL BACILO TUBERCULOSO EN ESPUTO, CON O SIN CULTIVO | D61: AMBOS | E61: 228 | F61: 599 | H61: Ver RN
A62: A151 | C62: TUBERCULOSIS DEL PULMON, CONFIRMADA UNICAMENTE POR CULTIVO | D62: AMBOS | E62: 228 | F62: 599 | H62: Ver RN
A63: A152 | C63: TUBERCULOSIS DEL PULMON, CONFIRMADA HISTOLOGICAMENTE | D63: AMBOS | E63: 228 | F63: 599 | H63: Ver RN
A64: A153 | C64: TUBERCULOSIS DEL PULMON , CONFIRMADA POR MEDIOS NO ESPECIFICADOS | D64: AMBOS | E64: 228 | F64: 599 | H64: Ver RN
A65: A154 | C65: TUBERCULOSIS DE GANGLIOS LINFATICOS INTRATORACICOS, CONFIRMADA BACTERIOLOGICA E HISTOLOGICAMENTE | D65: AMBOS | E65: 228 | F65: 599 | H65: Ver RN
A66: A155 | C66: TUBERCULOSIS DE LARINGE, TRAQUEA Y BRONQUIOS, CONFIRMADA BACTERIOLOGICA E HISTOLOGICAMENTE | D66: AMBOS | E66: 228 | F66: 599 | H66: Ver RN
A67: A156 | C67: PLEURESIA TUBERCULOSA, CONFIRMADA BACTERIOLOGICA E HISTOLOGICAMENTE | D67: AMBOS | E67: 228 | F67: 599 | H67: Ver RN
A68: A157 | C68: TUBERCULOSIS RESPIRATORIA PRIMARIA, CONFIRMADA BACTERIOLOGICA E HISTOLOGICAMENTE | D68: AMBOS | E68: 0 | F68: 0
A69: A158 | C69: OTRAS TUBERCULOSIS RESPIRATORIAS, CONFIRMADAS BACTERIOLOGICA E HISTOLOGICAMENTE | D69: AMBOS | E69: 228 | F69: 599 | H69: Ver RN
A70: A159 | C70: TUBERCULOSIS RESPIRATORIA NO ESPECIFICADA, CONFIRMADA BACTERIOLOGICAMENTE E HISTOLOGICAMENTE | D70: AMBOS | E70: 228 | F70: 599 | H70: Ver RN
A71: A160 | C71: TUBERCULOSIS DEL PULMON, CON EXAMEN BACTERIOLOGICO E HISTOLOGICO NEGATIVOS | D71: AMBOS | E71: 228 | F71: 599 | H71: Ver RN
A72: A161 | C72: TUBERCULOSIS DEL PULMON, SIN EXAMEN BACTERIOLOGICO E HISTOLOGICO | D72: AMBOS | E72: 228 | F72: 599 | H72: Ver RN
A73: A162 | C73: TUBERCULOSIS DE PULMON, SIN MENCION DE CONFIRMACION BACTERIOLOGICA O HISTOLOGICA | D73: AMBOS | E73: 228 | F73: 599 | H73: Ver RN
A74: A163 | C74: TUBERCULOSIS DE GANGLIOS LINFATICOS INTRATORACICOS, SIN MENCION DE CONFIRMACION BACTERIOLOGICA O HISTOLOGICA | D74: AMBOS | E74: 228 | F74: 599 | H74: Ver RN
A75: A164 | C75: TUBERCULOSIS DE LARINGE, TRAQUEA Y BRONQUIOS, SIN MENCION DE CONFIRMACION BACTERIOLOGICA O HISTOLOGICA | D75: AMBOS | E75: 228 | F75: 599 | H75: Ver RN
A76: A165 | C76: PLEURESIA TUBERCULOSA, SIN MENCION DE CONFIRMACION BACTERIOLOGICA E HISTOLOGICA | D76: AMBOS | E76: 228 | F76: 599 | H76: Ver RN
A77: A167 | C77: TUBERCULOSIS RESPIRATORIA PRIMARIA, SIN MENCION DE CONFIRMACION BACTERIOLOGICA E HISTOLOGICA | D77: AMBOS | E77: 228 | F77: 599 | H77: Ver RN
A78: A168 | C78: OTRAS TUBERCULOSIS RESPIRATORIAS, SIN MENCION DE CONFIRMACION | D78: AMBOS | E78: 228 | F78: 599 | H78: Ver RN
A79: A169 | C79: TUBERCULOSIS RESPIRATORIA NO ESPECIFICADA, SIN MENCION DE CONFIRMACION BACTERIOLOGICA O HISTOLOGICA | D79: AMBOS | E79: 228 | F79: 599 | H79: Ver RN
A80: A170 | B80: † | C80: MENINGITIS TUBERCULOSA (G01*) | D80: AMBOS | E80: 228 | F80: 599 | H80: Ver RN
A81: A171 | B81: † | C81: TUBERCULOMA MENINGEO (G07*) | D81: AMBOS | E81: 228 | F81: 599 | H81: Ver RN
A82: A178 | B82: † | C82: OTRAS TUBERCULOSIS DEL SISTEMA NERVIOSO | D82: AMBOS | E82: 228 | F82: 599 | H82: Ver RN
A83: A179 | B83: † | C83: TUBERCULOSIS DEL SISTEMA NERVIOSO, NO ESPECIFICADA (G99.8*) | D83: AMBOS | E83: 228 | F83: 599 | H83: Ver RN
A84: A180 | B84: † | C84: TUBERCULOSIS DE HUESOS Y ARTICULACIONES | D84: AMBOS | E84: 228 | F84: 599 | H84: Ver RN
A85: A181 | B85: † | C85: TUBERCULOSIS DEL APARATO GENITOURINARIO | D85: AMBOS | E85: 228 | F85: 599 | H85: Ver RN
A86: A182 | C86: LINFADENOPATIA PERIFERICA TUBERCULOSA | D86: AMBOS | E86: 228 | F86: 599 | H86: Ver RN
A87: A183 | C87: TUBERCULOSIS DE LOS INTESTINOS, EL PERITONEO Y LOS GANGLIOS MESENTERICOS | D87: AMBOS | E87: 228 | F87: 599 | H87: Ver RN
A88: A184 | C88: TUBERCULOSIS DE LA PIEL Y EL TEJIDO SUBCUTANEO | D88: AMBOS | E88: 0 | F88: 0
A89: A185 | B89: † | C89: TUBERCULOSIS DEL OJO | D89: AMBOS | E89: 228 | F89: 599 | H89: Ver RN
A90: A186 | B90: † | C90: TUBERCULOSIS DEL OIDO | D90: AMBOS | E90: 228 | F90: 599 | H90: Ver RN
A91: A187 | B91: † | C91: TUBERCULOSIS DE GLANDULAS SUPRARRENALES (E35.1*) | D91: AMBOS | E91: 228 | F91: 599 | H91: Ver RN
A92: A188 | B92: † | C92: TUBERCULOSIS DE OTROS ORGANOS ESPECIFICADOS | D92: AMBOS | E92: 228 | F92: 599 | H92: Ver RN
A93: A190 | C93: TUBERCULOSIS MILIAR AGUDA DE UN SOLO SITIO ESPECIFICADO | D93: AMBOS | E93: 228 | F93: 599 | H93: Ver RN
A94: A191 | C94: TUBERCULOSIS MILIAR AGUDA DE SITIOS MULTIPLES | D94: AMBOS | E94: 228 | F94: 599 | H94: Ver RN
A95: A192 | C95: TUBERCULOSIS MILIAR AGUDA, NO ESPECIFICADA | D95: AMBOS | E95: 228 | F95: 599 | H95: Ver RN
A96: A198 | C96: OTRAS TUBERCULOSIS MILIARES | D96: AMBOS | E96: 228 | F96: 599 | H96: Ver RN
A97: A199 | C97: TUBERCULOSIS MILIAR, SIN OTRA ESPECIFICACION | D97: AMBOS | E97: 228 | F97: 599 | H97: Ver RN
A98: A200 | C98: PESTE BUBONICA | D98: AMBOS | E98: 0 | F98: 0
A99: A201 | C99: PESTE CELULOCUTANEA | D99: AMBOS | E99: 0 | F99: 0
A100: A202 | C100: PESTE NEUMONICA | D100: AMBOS | E100: 0 | F100: 0
A101: A203 | C101: MENINGITIS POR PESTE | D101: AMBOS | E101: 0 | F101: 0
A102: A207 | C102: PESTE SEPTICEMICA | D102: AMBOS | E102: 0 | F102: 0
A103: A208 | C103: OTRAS FORMAS DE PESTE | D103: AMBOS | E103: 0 | F103: 0
A104: A209 | C104: PESTE, NO ESPECIFICADA | D104: AMBOS | E104: 0 | F104: 0
A105: A210 | C105: TULAREMIA ULCEROGLANDULAR | D105: AMBOS | E105: 0 | F105: 0
A106: A211 | C106: TULAREMIA OCULOGLANDULAR | D106: AMBOS | E106: 0 | F106: 0
A107: A212 | C107: TULAREMIA PULMONAR | D107: AMBOS | E107: 0 | F107: 0
A108: A213 | C108: TULAREMIA GASTROINTESTINAL | D108: AMBOS | E108: 0 | F108: 0
A109: A217 | C109: TULAREMIA GENERALIZADA | D109: AMBOS | E109: 0 | F109: 0
... A156: A320 | C156: LISTERIOSIS CUTANEA | D156: AMBOS | E156: 0 | F156: 0
A157: A321 | B157: † | C157: MENINGITIS Y MENINGOENCEFALITIS LISTERIANA | D157: AMBOS | E157: 0 | F157: 0
A158: A327 | C158: SEPTICEMIA LISTERIANA | D158: AMBOS | E158: 0 | F158: 0
A159: A328 | C159: OTRAS FORMAS DE LISTERIOSIS | D159: AMBOS | E159: 0 | F159: 0
A160: A329 | C160: LISTERIOSIS, NO ESPECIFICADA | D160: AMBOS | E160: 0 | F160: 0
A161: A33X | C161: TETANOS NEONATAL | D161: AMBOS | E161: 000 | F161: 227
A162: A34X | C162: TETANOS OBSTETRICO | D162: MUJER | E162: 410 | F162: 454
A163: A35X | C163: OTROS TETANOS | D163: AMBOS | E163: 228 | F163: 599 | H163: Ver RN
A164: A360 | C164: DIFTERIA FARINGEA | D164: AMBOS | E164: 0 | F164: 0
A165: A361 | C165: DIFTERIA NASOFARINGEA | D165: AMBOS | E165: 0 | F165: 0
A166: A362 | C166: DIFTERIA LARINGEA | D166: AMBOS | E166: 0 | F166: 0
...
